advsecurenet/__init__.py
advsecurenet/attacks/__init__.py
advsecurenet/attacks/attacker/__init__.py
advsecurenet/attacks/attacker/attacker.py
advsecurenet/attacks/attacker/ddp_attacker.py
advsecurenet/attacks/base/__init__.py
advsecurenet/attacks/base/adversarial_attack.py
advsecurenet/attacks/decision_based/__init__.py
advsecurenet/attacks/decision_based/boundary.py
advsecurenet/attacks/gradient_based/__init__.py
advsecurenet/attacks/gradient_based/cw.py
advsecurenet/attacks/gradient_based/deepfool.py
advsecurenet/attacks/gradient_based/fgsm.py
advsecurenet/attacks/gradient_based/lots.py
advsecurenet/attacks/gradient_based/pgd.py
advsecurenet/dataloader/__init__.py
advsecurenet/dataloader/data_loader_factory.py
advsecurenet/dataloader/distributed_eval_sampler.py
advsecurenet/datasets/__init__.py
advsecurenet/datasets/base_dataset.py
advsecurenet/datasets/dataset_factory.py
advsecurenet/datasets/targeted_adv_dataset.py
advsecurenet/datasets/Cifar10/__init__.py
advsecurenet/datasets/Cifar10/cifar10_dataset.py
advsecurenet/datasets/Custom/CustomDataset.py
advsecurenet/datasets/Custom/__init__.py
advsecurenet/datasets/ImageNet/__init__.py
advsecurenet/datasets/ImageNet/imagenet_dataset.py
advsecurenet/datasets/MNIST/__init__.py
advsecurenet/datasets/MNIST/mnist_dataset.py
advsecurenet/datasets/svhn/__init__.py
advsecurenet/datasets/svhn/svhn_dataset.py
advsecurenet/defenses/__init__.py
advsecurenet/defenses/adversarial_training.py
advsecurenet/defenses/ddp_adversarial_training.py
advsecurenet/distributed/__init__.py
advsecurenet/distributed/ddp_base_task.py
advsecurenet/distributed/ddp_coordinator.py
advsecurenet/evaluation/__init__.py
advsecurenet/evaluation/adversarial_evaluator.py
advsecurenet/evaluation/base_evaluator.py
advsecurenet/evaluation/tester.py
advsecurenet/evaluation/evaluators/__init__.py
advsecurenet/evaluation/evaluators/attack_success_rate_evaluator.py
advsecurenet/evaluation/evaluators/perturbation_distance_evaluator.py
advsecurenet-0.2.3.dist-info/LICENSE
advsecurenet-0.2.3.dist-info/METADATA
advsecurenet-0.2.3.dist-info/WHEEL
advsecurenet-0.2.3.dist-info/entry_points.txt
advsecurenet-0.2.3.dist-info/top_level.txt
advsecurenet-0.2.3.dist-info/RECORD
