Metadata-Version: 2.1
Name: advsecurenet
Version: 0.2.3
Summary: AdvSecureNet | Adversarial Secure Networks | Machine Learning Security
Home-page: https://github.com/melihcatal/advsecurenet
Author: Melih Catal
Author-email: melihcatal@gmail.com
Requires-Python: >=3.10
License-File: LICENSE
Requires-Dist: click
Requires-Dist: torch
Requires-Dist: torchvision
Requires-Dist: colored
Requires-Dist: tqdm
Requires-Dist: PyYAML
Requires-Dist: opencv-python
Requires-Dist: ruamel.yaml
Requires-Dist: matplotlib
Requires-Dist: scikit-image
Requires-Dist: einops
Requires-Dist: filetype
Requires-Dist: requests
